tapioca_discourse/__init__.py
tapioca_discourse/tapioca_discourse.py
tapioca_discourse/resource_mapping/__init__.py
tapioca_discourse/resource_mapping/about.py
tapioca_discourse/resource_mapping/admin.py
tapioca_discourse/resource_mapping/admin_emails.py
tapioca_discourse/resource_mapping/backups.py
tapioca_discourse/resource_mapping/badges.py
tapioca_discourse/resource_mapping/categories.py
tapioca_discourse/resource_mapping/emails.py
tapioca_discourse/resource_mapping/flags.py
tapioca_discourse/resource_mapping/groups.py
tapioca_discourse/resource_mapping/invites.py
tapioca_discourse/resource_mapping/logs.py
tapioca_discourse/resource_mapping/notifications.py
tapioca_discourse/resource_mapping/password_reset.py
tapioca_discourse/resource_mapping/plugins.py
tapioca_discourse/resource_mapping/polls.py
tapioca_discourse/resource_mapping/posts.py
tapioca_discourse/resource_mapping/private_messages.py
tapioca_discourse/resource_mapping/reports.py
tapioca_discourse/resource_mapping/search.py
tapioca_discourse/resource_mapping/tags.py
tapioca_discourse/resource_mapping/topics.py
tapioca_discourse/resource_mapping/upload.py
tapioca_discourse/resource_mapping/user_fields.py
tapioca_discourse/resource_mapping/users.py
tapioca_discourse/resource_mapping/webhooks.py
tapioca_discourse-0.1.2.dist-info/DESCRIPTION.rst
tapioca_discourse-0.1.2.dist-info/METADATA
tapioca_discourse-0.1.2.dist-info/RECORD
tapioca_discourse-0.1.2.dist-info/WHEEL
tapioca_discourse-0.1.2.dist-info/metadata.json
tapioca_discourse-0.1.2.dist-info/top_level.txt
tests/__init__.py
tests/test_tapioca_discourse.py
